gemini_gen_mcp/__init__.py
gemini_gen_mcp/server.py
gemini_gen_mcp-0.0.4.dist-info/METADATA
gemini_gen_mcp-0.0.4.dist-info/WHEEL
gemini_gen_mcp-0.0.4.dist-info/entry_points.txt
gemini_gen_mcp-0.0.4.dist-info/licenses/LICENSE
gemini_gen_mcp-0.0.4.dist-info/RECORD
