Metadata-Version: 2.4
Name: gemini-gen-mcp
Version: 0.0.4
Summary: MCP Server for Gemini Image and Audio generation
Project-URL: Homepage, https://github.com/ServiceStack/gemini-gen-mcp
Project-URL: Repository, https://github.com/ServiceStack/gemini-gen-mcp
Author-email: ServiceStack <team@servicestack.net>
License: MIT
License-File: LICENSE
Keywords: ai,audio-generation,gemini,image-generation,mcp,tts
Classifier: Development Status :: 3 - Alpha
Classifier: Intended Audience :: Developers
Classifier: License :: OSI Approved :: MIT License
Classifier: Programming Language :: Python :: 3
Classifier: Programming Language :: Python :: 3.10
Classifier: Programming Language :: Python :: 3.11
Classifier: Programming Language :: Python :: 3.12
Requires-Python: >=3.10
Requires-Dist: fastmcp>=0.1.0
Requires-Dist: google-genai>=1.0.0
